Workbook
Name aporte: [1]APP!$D$17
Name patrimonio: [1]APP!$D$20
Name qtd_anos: [1]APP!$D$18
Name rendimento_carteira: [1]APP!$D$13
Name taxa_mensal: [1]APP!$D$19

Sheet APP
B1: INVE$T
B4: INFORMAÇÕES
B5: Salário | D5: 2000
B6: Rendimento Carteira | D6: 0.006
B7: Sugestão de Investimento (30%) | D7: =D5*30% -> 600
B9: INVESTIMENTO MENSAL
B10: Quanto investir por mês | D10: 200
B11: Durante quantos Anos | D11: 5
B12: Taxa de Rendimento mensal | D12: 0.01079
B13: Patrimônio acumulado | D13: =FV(taxa_mensal,qtd_anos*12,aporte*-1) -> 16755.383
B14: Dividendos Mensais | D14: =patrimonio*rendimento_carteira -> 100.5323
B16: CENÁRIOS | D16: DIVIDENDO
B17: Valor em 2 anos: | C17: =FV($D$12,$A24*12,$D$10*-1) -> 5445.5255 | D17: =C17*rendimento_carteira -> 32.673153
B18: Valor em 5 anos: | C18: =FV($D$12,$A25*12,$D$10*-1) -> 16755.383 | D18: =C18*rendimento_carteira -> 100.5323
B19: Valor em 10 anos: | C19: =FV($D$12,$A26*12,$D$10*-1) -> 48656.843 | D19: =C19*rendimento_carteira -> 291.94106
B20: Valor em 20 anos: | C20: =FV($D$12,$A27*12,$D$10*-1) -> 225039.68 | D20: =C20*rendimento_carteira -> 1350.2381
B21: Valor em 30 anos: | C21: =FV($D$12,$A28*12,$D$10*-1) -> 864433.93 | D21: =C21*rendimento_carteira -> 5186.6036
B23: PERFIL DO INVESTIDOR | C23: Moderado
A24: 2 | B24: VALOR A INVESTIR POR MÊS | C24: =aporte -> 200
A25: 5
A26: 10 | B26: TIPO DE FII | C26: % Sugerido | D26: Valores
A27: 20 | B27: PAPEL | C27: =VLOOKUP($C$23&"-"&B27,BD!$A:$D,4,FALSE) -> 0.32 | D27: =C27*$C$24 -> 64
A28: 30 | B28: TIJOLO | C28: =VLOOKUP($C$23&"-"&B28,BD!$A:$D,4,FALSE) -> 0.35 | D28: =C28*$C$24 -> 70
B29: HÍBRIDOS | C29: =VLOOKUP($C$23&"-"&B29,BD!$A:$D,4,FALSE) -> 0.08 | D29: =C29*$C$24 -> 16
B30: FOFs | C30: =VLOOKUP($C$23&"-"&B30,BD!$A:$D,4,FALSE) -> 0.05 | D30: =C30*$C$24 -> 10
B31: DESENVOLVIMENTO | C31: =VLOOKUP($C$23&"-"&B31,BD!$A:$D,4,FALSE) -> 0.1 | D31: =C31*$C$24 -> 20
B32: HOTELARIAS | C32: =VLOOKUP($C$23&"-"&B32,BD!$A:$D,4,FALSE) -> 0.1 | D32: =C32*$C$24 -> 20
C33: =SUM(C27:C32) -> 1 | D33: =SUM(D27:D32) -> 200

Sheet BD
A2: CHAVE | B2: PERFIL | C2: TIPO DE FII | D2: %
A3: =B3&"-"&C3 -> Conservador-PAPEL | B3: Conservador | C3: PAPEL | D3: 0.3 | H3: %
A4: =B4&"-"&C4 -> Conservador-TIJOLO | B4: Conservador | C4: TIJOLO | D4: 0.5 | G4: Moderado - TIJOLO | H4: =VLOOKUP(G4,$A:$D,4,FALSE) -> #N/A
A5: =B5&"-"&C5 -> Conservador-HÍBRIDOS | B5: Conservador | C5: HÍBRIDOS | D5: 0.1
A6: =B6&"-"&C6 -> Conservador-FOFs | B6: Conservador | C6: FOFs | D6: 0.1
A7: =B7&"-"&C7 -> Conservador-DESENVOLVIMENTO | B7: Conservador | C7: DESENVOLVIMENTO | D7: 0
A8: =B8&"-"&C8 -> Conservador-HOTELARIAS | B8: Conservador | C8: HOTELARIAS | D8: 0
A9: =B9&"-"&C9 -> Moderado-PAPEL | B9: Moderado | C9: PAPEL | D9: 0.32
A10: =B10&"-"&C10 -> Moderado-TIJOLO | B10: Moderado | C10: TIJOLO | D10: 0.35
A11: =B11&"-"&C11 -> Moderado-HÍBRIDOS | B11: Moderado | C11: HÍBRIDOS | D11: 0.08
A12: =B12&"-"&C12 -> Moderado-FOFs | B12: Moderado | C12: FOFs | D12: 0.05
A13: =B13&"-"&C13 -> Moderado-DESENVOLVIMENTO | B13: Moderado | C13: DESENVOLVIMENTO | D13: 0.1
A14: =B14&"-"&C14 -> Moderado-HOTELARIAS | B14: Moderado | C14: HOTELARIAS | D14: 0.1
A15: =B15&"-"&C15 -> Agressivo-PAPEL | B15: Agressivo | C15: PAPEL | D15: 0.5
A16: =B16&"-"&C16 -> Agressivo-TIJOLO | B16: Agressivo | C16: TIJOLO | D16: 0.1
... A20: =B20&"-"&C20 -> Agressivo-HOTELARIAS | B20: Agressivo | C20: HOTELARIAS | D20: 0.1
